{
  "Research": [
    {
      "Name": "Satiate more hunger per food",
      "Target": 120,
      "Modifiers": [
        {
          "Food": "1.1"
        }
      ],
      "Max Level": 20
    },
    {
      "Name": "Increase damage",
      "Target": 120,
      "Modifiers": [
        {
          "Damage": "1.1"
        }
      ],
      "Max Level": 20
    },
    {
      "Name": "Increase reach",
      "Target": 120,
      "Modifiers": [
        {
          "Reach": "1.1"
        }
      ],
      "Max Level": 20
    },
    {
      "Name": "Increase health",
      "Target": 120,
      "Modifiers": [
        {
          "Health": "1.1"
        }
      ],
      "Max Level": 20
    },
    {
      "Name": "Increase fertility",
      "Target": 120,
      "Modifiers": [
        {
          "Fertility": "1.1"
        }
      ],
      "Max Level": 20
    },
    {
      "Name": "Increase Awareness",
      "Target": 120,
      "Modifiers": [
        {
          "Awareness": "1.1"
        }
      ],
      "Max Level": 20
    },
    {
      "Name": "Unlock ancient buildings",
      "Target": 960,
      "Modifiers": [
        {

        }
      ],
      "Max Level": 1
    },
    {
      "Name": "Extend hunger time",
      "Target": 120,
      "Modifiers": [
        {
          "Hunger": "1.1"
        }
      ],
      "Max Level": 20
    },
    {
      "Name": "Extend energy time",
      "Target": 120,
      "Modifiers": [
        {
          "Energy": "1.1"
        }
      ],
      "Max Level": 20
    },
    {
      "Name": "Increase Speed",
      "Target": 120,
      "Modifiers": [
        {
          "Speed": "1.1"
        }
      ],
      "Max Level": 20
    },
    {
      "Name": "Increase Productivity",
      "Target": 120,
      "Modifiers": [
        {
          "Productivity": "1.1"
        }
      ],
      "Max Level": 20
    }
  ]
}